{
  "main": {
    "id": "main",
    "type": "split",
    "children": [
      {
        "id": "bbc67dc81c30c10b",
        "type": "tabs",
        "children": [
          {
            "id": "07142c10cf71dacd",
            "type": "leaf",
            "state": {
              "type": "graph",
              "state": {},
              "icon": "lucide-git-fork",
              "title": "Graph view"
            }
          }
        ]
      }
    ],
    "direction": "vertical"
  },
  "left": {
    "id": "left",
    "type": "split",
    "children": [
      {
        "id": "left-leaf",
        "type": "tabs",
        "children": [
          {
            "id": "file-explorer",
            "type": "leaf",
            "state": {
              "type": "file-explorer",
              "state": {
                "sortOrder": "alphabetical",
                "autoReveal": false
              },
              "icon": "lucide-folder-closed",
              "title": "Files"
            }
          },
          {
            "id": "search",
            "type": "leaf",
            "state": {
              "type": "search",
              "state": {
                "query": "",
                "matchingCase": false,
                "explainSearch": false,
                "collapseAll": false,
                "extraContext": false,
                "sortOrder": "alphabetical"
              },
              "icon": "lucide-search",
              "title": "Search"
            }
          },
          {
            "id": "4d5aa5e9efcb143c",
            "type": "leaf",
            "state": {
              "type": "bookmarks",
              "state": {},
              "icon": "lucide-bookmark",
              "title": "Bookmarks"
            }
          }
        ]
      }
    ],
    "direction": "horizontal",
    "width": 250
  },
  "right": {
    "id": "right",
    "type": "split",
    "children": [
      {
        "id": "right-leaf",
        "type": "tabs",
        "children": [
          {
            "id": "backlinks",
            "type": "leaf",
            "state": {
              "type": "backlink",
              "state": {
                "collapseAll": true,
                "extraContext": false,
                "sortOrder": "alphabetical",
                "showSearch": true,
                "searchQuery": "",
                "backlinkCollapsed": false,
                "unlinkedCollapsed": true
              },
              "icon": "links-coming-in",
              "title": "Backlinks"
            }
          },
          {
            "id": "325cb7bb9454386c",
            "type": "leaf",
            "state": {
              "type": "outline",
              "state": {
                "followCursor": false,
                "showSearch": false,
                "searchQuery": ""
              },
              "icon": "lucide-list",
              "title": "Outline"
            }
          }
        ]
      }
    ],
    "direction": "horizontal",
    "width": 407.5,
    "collapsed": true
  },
  "active": "07142c10cf71dacd",
  "lastOpenFiles": []
}
